sysom_cmd/__init__.py
sysom_cmd/__main__.py
sysom_cmd/main.py
sysom_cmd-0.1.1.dist-info/entry_points.txt
sysom_cmd-0.1.1.dist-info/WHEEL
sysom_cmd-0.1.1.dist-info/METADATA
sysom_cmd-0.1.1.dist-info/RECORD
