Metadata-Version: 2.1
Name: sysom-cmd
Version: 0.1.1
Summary: 
Author: SunnyQjm
Author-email: mfeng@linux.alibaba.com
Requires-Python: >=3.6,<4.0
Classifier: Programming Language :: Python :: 3
Classifier: Programming Language :: Python :: 3.10
Classifier: Programming Language :: Python :: 3.6
Classifier: Programming Language :: Python :: 3.7
Classifier: Programming Language :: Python :: 3.8
Classifier: Programming Language :: Python :: 3.9
Requires-Dist: typer[all] (>=0.9.0,<0.10.0)
